{
  "neoforge:conditions": [
    {
      "type": "neoforge:not",
      "value": {
        "type": "neoforge:tag_empty",
        "tag": "c:dusts/platinum"
      }
    },
    {
      "type": "ftbmaterials:components_available",
      "used_materials": [
        "platinum_ingot"
      ]
    }
  ],
  "type": "minecraft:blasting",
  "category": "misc",
  "cookingtime": 100,
  "experience": 0.7,
  "ingredient": "#c:dusts/platinum",
  "result": {
    "id": "ftbmaterials:platinum_ingot"
  },
  "show_notification": false
}