{
	"parent": "minecraft:block/block",
	"textures": {
		"texture": "ftbic:block/copper_wire",
		"particle": "ftbic:block/copper_wire"
	},
	"elements": [
		{
			"from": [
				6,
				0,
				6
			],
			"to": [
				10,
				6,
				10
			],
			"faces": {
				"down": {
					"texture": "#texture",
					"cullface": "down"
				},
				"north": {
					"texture": "#texture"
				},
				"south": {
					"texture": "#texture"
				},
				"west": {
					"texture": "#texture"
				},
				"east": {
					"texture": "#texture"
				}
			}
		}
	]
}